{
    "@class": "com.kony.gen.viz.model.component.KVizButton",
    "DNDConfig": null,
    "__parentReadjusting__": false,
    "_height_": {
        "type": "string",
        "value": "100%"
    },
    "_left_": {
        "type": "string",
        "value": "0.06%"
    },
    "_margin_": [
        6,
        6,
        6,
        6
    ],
    "_padding_": [
        0,
        0,
        0,
        0
    ],
    "_skin_": "s2b94baf2e994a53914ff1d171f57daf",
    "_text_": "",
    "_top_": {
        "type": "string",
        "value": "0.00%"
    },
    "_width_": {
        "type": "string",
        "value": "14%"
    },
    "canUpdateUI": true,
    "containerId": true,
    "containerweight": 100,
    "contentalignment": 5,
    "displaytext": true,
    "focusskin": "s4ca6c3fa6db410597f104a2674e356a",
    "id": "Button0692b2239355a41",
    "ide_onClick": "AS_Button_2c286f4c8f184a4a95f8f626dc90e0a6",
    "info": null,
    "iphone": {
        "psp": {
            "showProgressIndicator": false
        }
    },
    "isvisible": true,
    "kuid": "a12c27e733524389a784c90186c103bb",
    "name": "kony.ui.Button",
    "onclick": "AS_Button_8f8e31ef36264751a98f229f21d598df",
    "parent": "FlexScrollContainer02fc69c09b4074e",
    "pf": "frmEditTool",
    "wType": "Button"
}