{
    "@class": "com.kony.gen.viz.model.component.KVizButton",
    "DNDConfig": null,
    "__parentReadjusting__": false,
    "_height_": {
        "type": "string",
        "value": "44dp"
    },
    "_left_": {
        "type": "string",
        "value": "77.33%"
    },
    "_margin_": [
        6,
        6,
        6,
        6
    ],
    "_padding_": [
        0,
        0,
        0,
        0
    ],
    "_skin_": "s0239886674546bfb6fafd1c9eaef4d6",
    "_text_": "",
    "_top_": {
        "type": "string",
        "value": "6dp"
    },
    "_width_": {
        "type": "string",
        "value": "20%"
    },
    "canUpdateUI": true,
    "containerweight": 100,
    "contentalignment": 5,
    "displaytext": true,
    "focusskin": "s26bdf3bcfee4930a21fed04b784535e",
    "id": "Button0eb92b74f4c1848",
    "ide_onTouchEnd": "AS_Button_f6f588a0e63247fd87c48b27a882e391",
    "info": null,
    "isvisible": true,
    "kuid": "9f94de20d3e3493a8f66cc6201cb9c0d",
    "name": "kony.ui.Button",
    "parent": "FlexContainer0344ae25ce9564f",
    "pf": "frmtwoImagesIphone",
    "wType": "Button",
    "zindex": 1
}